clipdump/__init__.py
clipdump/main.py
clipdump-1.0.2.dist-info/METADATA
clipdump-1.0.2.dist-info/WHEEL
clipdump-1.0.2.dist-info/entry_points.txt
clipdump-1.0.2.dist-info/top_level.txt
clipdump-1.0.2.dist-info/RECORD
