Metadata-Version: 2.2
Name: clipdump
Version: 1.0.2
Summary: A simple CLI tool to save and append clipboard contents.
Home-page: https://github.com/yourusername/clipdump
Author: Backspace Studios
Classifier: Programming Language :: Python :: 3
Classifier: Operating System :: OS Independent
Classifier: Environment :: Console
Classifier: Intended Audience :: End Users/Desktop
Classifier: License :: OSI Approved :: MIT License
Classifier: Topic :: Utilities
Requires-Python: >=3.6
Requires-Dist: pyperclip
Dynamic: author
Dynamic: classifier
Dynamic: description
Dynamic: description-content-type
Dynamic: home-page
Dynamic: requires-dist
Dynamic: requires-python
Dynamic: summary
